scblender/__init__.py
scblender/curve.py
scblender/frame.py
scblender/mesh.py
scblender/particle.py
scblender/setting.py
scblender-0.0.1.dist-info/METADATA
scblender-0.0.1.dist-info/WHEEL
scblender-0.0.1.dist-info/top_level.txt
scblender-0.0.1.dist-info/RECORD
